cardinal/__init__.py
cardinal/base.py
cardinal/batch.py
cardinal/cache.py
cardinal/clustering.py
cardinal/kmeans.py
cardinal/metrics.py
cardinal/plotting.py
cardinal/random.py
cardinal/submodularity.py
cardinal/typeutils.py
cardinal/uncertainty.py
cardinal/utils.py
cardinal/version.py
cardinal/zhdanov2019.py
cardinal/tests/__init__.py
cardinal/tests/test_cache.py
cardinal/tests/test_clustering.py
cardinal/tests/test_uncertainty.py
cardinal/tests/test_utils.py
cardinal-0.0.9.dist-info/LICENSE.txt
cardinal-0.0.9.dist-info/METADATA
cardinal-0.0.9.dist-info/NOTICE
cardinal-0.0.9.dist-info/WHEEL
cardinal-0.0.9.dist-info/top_level.txt
cardinal-0.0.9.dist-info/RECORD
