Metadata-Version: 2.1
Name: cardinal
Version: 0.0.9
Summary: Active learning python package
Home-page: https://dataiku-research.github.io/cardinal
Download-URL: https://github.com/dataiku-research/cardinal
Maintainer: Alexandre Abraham
Maintainer-email: alexandre.abraham@dataiku.com
License: Apache 2.0
Classifier: Intended Audience :: Science/Research
Classifier: Intended Audience :: Developers
Classifier: Programming Language :: Python
Classifier: Topic :: Scientific/Engineering
Classifier: Operating System :: Microsoft :: Windows
Classifier: Operating System :: POSIX
Classifier: Operating System :: Unix
Classifier: Operating System :: MacOS
Classifier: Programming Language :: Python :: 3.5
Classifier: Programming Language :: Python :: 3.6
Classifier: Programming Language :: Python :: 3.7
Requires-Python: >=3.5
License-File: LICENSE.txt
License-File: NOTICE
Requires-Dist: numpy (>=1.11)
Requires-Dist: scipy (>=0.19)
Provides-Extra: all
Requires-Dist: scikit-learn (>=0.23) ; extra == 'all'
Requires-Dist: apricot-select (>=0.5.0) ; extra == 'all'
Requires-Dist: matplotlib (>=2.0) ; extra == 'all'
Requires-Dist: sphinx-gallery (>=0.5.0) ; extra == 'all'
Requires-Dist: sphinx (>=2.2.2) ; extra == 'all'
Provides-Extra: doc
Requires-Dist: scikit-learn (>=0.23) ; extra == 'doc'
Requires-Dist: apricot-select (>=0.5.0) ; extra == 'doc'
Requires-Dist: matplotlib (>=2.0) ; extra == 'doc'
Requires-Dist: sphinx-gallery (>=0.5.0) ; extra == 'doc'
Requires-Dist: sphinx (>=2.2.2) ; extra == 'doc'
Provides-Extra: examples
Requires-Dist: scikit-learn (>=0.23) ; extra == 'examples'
Requires-Dist: matplotlib (>=2.0) ; extra == 'examples'
Provides-Extra: sklearn
Requires-Dist: scikit-learn (>=0.23) ; extra == 'sklearn'
Provides-Extra: submodular
Requires-Dist: scikit-learn (>=0.23) ; extra == 'submodular'
Requires-Dist: apricot-select (>=0.5.0) ; extra == 'submodular'
